CHANGES.txt
Makefile
README.txt
setup.py
version.txt
raisin/__init__.py
raisin.recipe.server.egg-info/PKG-INFO
raisin.recipe.server.egg-info/SOURCES.txt
raisin.recipe.server.egg-info/dependency_links.txt
raisin.recipe.server.egg-info/entry_points.txt
raisin.recipe.server.egg-info/namespace_packages.txt
raisin.recipe.server.egg-info/not-zip-safe
raisin.recipe.server.egg-info/requires.txt
raisin.recipe.server.egg-info/top_level.txt
raisin/recipe/__init__.py
raisin/recipe/server/__init__.py
raisin/recipe/server/server.py
raisin/recipe/server/tests/README.txt
raisin/recipe/server/tests/__init__.py
raisin/recipe/server/tests/test_recipe.py
raisin/recipe/server/tests/control/etc/connections/mysql.ini
raisin/recipe/server/tests/control/etc/databases/databases.ini
raisin/recipe/server/tests/control/etc/misc/parameters.ini
raisin/recipe/server/tests/control/etc/misc/project_parameters.ini
raisin/recipe/server/tests/control/etc/projects/projects.ini
raisin/recipe/server/tests/control/etc/pyramid/development.ini
raisin/recipe/server/tests/control/etc/pyramid/projects.ini
raisin/recipe/server/tests/control/etc/pyramid/users.ini
raisin/recipe/server/tests/control/etc/restish/development.ini
raisin/recipe/server/tests/control/etc/restish/raisin.restish.ini
raisin/recipe/server/tests/control/etc/supervisor/development.conf
raisin/recipe/server/tests/control/etc/supervisor/production.conf